flowdeploy/__init__.py
flowdeploy/cli/__init__.py
flowdeploy/cli/cli.py
flowdeploy/client.py
flowdeploy/exceptions.py
flowdeploy/keys.py
flowdeploy-0.4.0.dist-info/LICENSE
flowdeploy-0.4.0.dist-info/METADATA
flowdeploy-0.4.0.dist-info/WHEEL
flowdeploy-0.4.0.dist-info/entry_points.txt
flowdeploy-0.4.0.dist-info/RECORD
