Metadata-Version: 2.1
Name: flowdeploy
Version: 0.4.0
Summary: Use with your favorite bioinformatics manager – like Nextflow or Snakemake – to develop and deploy bioinformatics pipelines quickly
Home-page: https://flowdeploy.com
Author: Noah Lebovic
Author-email: security@trytoolchest.com
Requires-Python: >=3.9,<4.0
Classifier: Programming Language :: Python :: 3
Classifier: Programming Language :: Python :: 3.9
Classifier: Programming Language :: Python :: 3.10
Classifier: Programming Language :: Python :: 3.11
Requires-Dist: boto3 (>=1.28.8,<2.0.0)
Requires-Dist: loguru (>=0.7.0,<0.8.0)
Requires-Dist: pytest (>=7.4.0,<8.0.0)
Requires-Dist: requests (>=2.31.0,<3.0.0)
Requires-Dist: rich (>=13.7.0,<14.0.0)
Requires-Dist: typer (>=0.9.0,<0.10.0)
